yen_parser/__init__.py
yen_parser/parse_yen.py
yen_parser-0.1.0.dist-info/LICENSE
yen_parser-0.1.0.dist-info/WHEEL
yen_parser-0.1.0.dist-info/METADATA
yen_parser-0.1.0.dist-info/RECORD
