Metadata-Version: 2.1
Name: yen-parser
Version: 0.1.0
Summary: Yen currency string parser.
Home-page: https://github.com/kendimaru/yen-parser
License: MIT
Keywords: Japanese,yen,currency,parse
Author: kenjimaru
Author-email: kendimaru2@gmail.com
Maintainer: kenjimaru
Maintainer-email: kendimaru2@gmail.com
Requires-Python: >=3.6,<4.0
Classifier: Development Status :: 3 - Alpha
Classifier: Intended Audience :: Developers
Classifier: License :: OSI Approved :: MIT License
Classifier: Programming Language :: Python :: 3
Classifier: Programming Language :: Python :: 3.6
Classifier: Programming Language :: Python :: 3.7
Classifier: Programming Language :: Python :: 3.8
Classifier: Programming Language :: Python :: 3.9
Project-URL: Repository, https://github.com/kendimaru/yen-parser
